<?xml version="1.0"?>
<opencv_storage>
<obj>
  <_><id>1</id>
    <height>4.2985677719116211e-02</height>
    <contour2d>
      5.78368604e-01 -6.11014292e-02 5.76784015e-01 -5.60858324e-02
      5.71298003e-01 -4.84142788e-02 5.61637580e-01 -4.07053120e-02
      5.58769226e-01 -3.94052379e-02 5.52670538e-01 -3.79971303e-02
      5.46315134e-01 -3.77782658e-02 5.41502535e-01 -3.88035811e-02
      5.38274527e-01 -3.98754105e-02 5.35700679e-01 -4.10006866e-02
      5.32054842e-01 -4.32018489e-02 5.27894437e-01 -4.66069691e-02
      5.25858164e-01 -4.88416627e-02 5.22865176e-01 -5.34093194e-02
      5.21192968e-01 -5.68327084e-02 5.20108163e-01 -6.03278764e-02
      5.19592583e-01 -6.25956133e-02 5.19285202e-01 -6.48899972e-02
      5.19134939e-01 -6.83761239e-02 5.19358039e-01 -7.19241798e-02
      5.19720554e-01 -7.43297562e-02 5.21223187e-01 -7.91263282e-02
      5.22961974e-01 -8.28072801e-02 5.24372220e-01 -8.52571130e-02
      5.26401162e-01 -8.78402591e-02 5.27582109e-01 -8.90739560e-02
      5.30454636e-01 -9.16543379e-02 5.32373071e-01 -9.30525139e-02
      5.37638247e-01 -9.57658365e-02 5.42462885e-01 -9.74053293e-02
      5.48511028e-01 -9.79107544e-02 5.54844141e-01 -9.72608328e-02
      5.58037519e-01 -9.63267908e-02 5.63040078e-01 -9.43433195e-02
      5.68049967e-01 -9.11093950e-02 5.71200192e-01 -8.76688063e-02
      5.74706793e-01 -8.30395073e-02 5.78213334e-01 -7.46692568e-02</contour2d>
    <histogram type_id="opencv-matrix">
      <rows>20</rows>
      <cols>1</cols>
      <dt>f</dt>
      <data>
        0. 0. 0. 0. 0. 0. 0. 0. 0. 0. 1. 0. 0. 0. 0. 0. 0. 0. 0. 0.</data></histogram></_>
  <_><id>2</id>
    <height>4.2956650257110596e-02</height>
    <contour2d>
      5.78127742e-01 -5.61303459e-02 5.78013301e-01 -3.75957489e-02
      5.76188982e-01 -3.38302776e-02 5.71456075e-01 -2.63320282e-02
      5.63441277e-01 -2.00539362e-02 5.57006836e-01 -1.75147038e-02
      5.43299019e-01 -1.73118804e-02 5.38913131e-01 -1.84436888e-02
      5.36712646e-01 -1.95805002e-02 5.31567276e-01 -2.30257194e-02
      5.28766274e-01 -2.53373440e-02 5.27642787e-01 -2.65063085e-02
      5.25737941e-01 -2.88011227e-02 5.24221420e-01 -3.11133768e-02
      5.22874415e-01 -3.34322788e-02 5.21398008e-01 -3.69088463e-02
      5.20084918e-01 -4.27366868e-02 5.19767165e-01 -4.62190360e-02
      5.20157218e-01 -5.09531759e-02 5.21410584e-01 -5.68622611e-02
      5.23044288e-01 -6.04860522e-02 5.24429381e-01 -6.29066303e-02
      5.27224422e-01 -6.65867031e-02 5.29834211e-01 -6.90690875e-02
      5.32946706e-01 -7.16425404e-02 5.34810722e-01 -7.29857758e-02
      5.37891030e-01 -7.43819997e-02 5.42319238e-01 -7.58542344e-02
      5.53546667e-01 -7.66486749e-02 5.59420943e-01 -7.45737478e-02
      5.64520776e-01 -7.24995136e-02 5.67791522e-01 -7.02659860e-02
      5.74562192e-01 -6.33216873e-02</contour2d>
    <histogram type_id="opencv-matrix">
      <rows>20</rows>
      <cols>1</cols>
      <dt>f</dt>
      <data>
        0. 0. 0. 0. 0. 0. 0. 0. 0. 2.01106095e-03 9.97988999e-01 0. 0.
        0. 0. 0. 0. 0. 0. 0.</data></histogram></_>
  <_><id>3</id>
    <height>4.2899727821350098e-02</height>
    <contour2d>
      5.38807094e-01 -1.24444440e-02 5.36969066e-01 -6.47563720e-03
      5.35445511e-01 -2.90590222e-03 5.30793071e-01 4.19759192e-03
      5.21953046e-01 1.12007027e-02 5.18767953e-01 1.23333605e-02
      5.09317815e-01 1.45620964e-02 5.01573384e-01 1.32952146e-02
      4.97985184e-01 1.21171903e-02 4.93239105e-01 9.76923387e-03
      4.88571614e-01 6.30969135e-03 4.87461179e-01 5.17020421e-03
      4.84784245e-01 1.75844482e-03 4.83277261e-01 -5.07154269e-04
      4.81521040e-01 -3.89232161e-03 4.80318934e-01 -7.27252290e-03
      4.79764372e-01 -9.51417442e-03 4.79127616e-01 -1.29010864e-02
      4.78976309e-01 -1.62752401e-02 4.79897588e-01 -2.30362825e-02
      4.80529398e-01 -2.53317710e-02 4.81367975e-01 -2.75853537e-02
      4.83080626e-01 -3.10379248e-02 4.84455496e-01 -3.33421938e-02
      4.87375170e-01 -3.68486494e-02 4.88543749e-01 -3.80117446e-02
      4.91457969e-01 -4.04024608e-02 4.95484024e-01 -4.28289361e-02
      4.98371989e-01 -4.40948009e-02 5.02611220e-01 -4.54170480e-02
      5.11039138e-01 -4.57551442e-02 5.17265320e-01 -4.48759012e-02
      5.20229697e-01 -4.38279770e-02 5.30563056e-01 -3.59646864e-02
      5.35251260e-01 -2.90059261e-02 5.36787391e-01 -2.54822914e-02
      5.38538098e-01 -1.83883961e-02</contour2d>
    <histogram type_id="opencv-matrix">
      <rows>20</rows>
      <cols>1</cols>
      <dt>f</dt>
      <data>
        0. 0. 0. 0. 0. 0. 0. 0. 0. 4.85908648e-04 9.98542249e-01 0. 0.
        0. 0. 0. 0. 0. 0. 9.71817295e-04</data></histogram></_>
  <_><id>4</id>
    <height>4.2878866195678711e-02</height>
    <contour2d>
      5.07795155e-01 2.25982964e-02 5.04864812e-01 2.94512250e-02
      5.01996040e-01 3.39712277e-02 4.99321371e-01 3.73376198e-02
      4.95099813e-01 4.06206883e-02 4.90535468e-01 4.26989011e-02
      4.87652153e-01 4.37108204e-02 4.83456612e-01 4.46649939e-02
      4.70829219e-01 4.42107208e-02 4.67393100e-01 4.28946838e-02
      4.64731216e-01 4.16762307e-02 4.59958345e-01 3.82081121e-02
      4.58646983e-01 3.70559245e-02 4.56460446e-01 3.47173177e-02
      4.53943461e-01 3.13454941e-02 4.51514721e-01 2.68993918e-02
      4.50317770e-01 2.35895161e-02 4.49572653e-01 1.91700868e-02
      4.49364632e-01 1.47923650e-02 4.49502826e-01 1.15222959e-02
      4.49767172e-01 9.34543833e-03 4.51319277e-01 3.88910947e-03
      4.52848911e-01 6.05258974e-04 4.55074340e-01 -2.68993317e-03
      4.56792563e-01 -4.89917537e-03 4.58976567e-01 -7.11103762e-03
      4.63313311e-01 -1.04700373e-02 4.67319012e-01 -1.27352728e-02
      4.71136808e-01 -1.38930781e-02 4.79907781e-01 -1.51507631e-02
      4.86253321e-01 -1.40952123e-02 4.91773009e-01 -1.18908761e-02
      4.97817963e-01 -8.53018276e-03 5.01774371e-01 -3.96169350e-03
      5.06320119e-01 2.94521870e-03 5.07732093e-01 7.57146440e-03</contour2d>
    <histogram type_id="opencv-matrix">
      <rows>20</rows>
      <cols>1</cols>
      <dt>f</dt>
      <data>
        0. 0. 0. 0. 0. 0. 0. 0. 0. 9.62000981e-04 9.98076022e-01 0. 0.
        0. 0. 0. 0. 0. 0. 9.62000981e-04</data></histogram></_>
  <_><id>5</id>
    <height>4.2694926261901855e-02</height>
    <contour2d>
      4.62390989e-01 3.48745286e-02 4.62363303e-01 4.03980240e-02
      4.61027056e-01 4.69677635e-02 4.59664196e-01 5.02090305e-02
      4.55695748e-01 5.66014983e-02 4.51757669e-01 6.07569478e-02
      4.49107289e-01 6.27745390e-02 4.45018619e-01 6.46677986e-02
      4.39766496e-01 6.64747655e-02 4.36026484e-01 6.73119351e-02
      4.23763841e-01 6.65175244e-02 4.16287303e-01 6.28305078e-02
      4.12172765e-01 5.95097244e-02 4.08138871e-01 5.50191738e-02
      4.06767488e-01 5.28294295e-02 4.04464096e-01 4.85419668e-02
      4.02995527e-01 4.21937667e-02 4.02761459e-01 3.69624086e-02
      4.03215528e-01 3.18120420e-02 4.04537410e-01 2.66504437e-02
      4.05523330e-01 2.45781373e-02 4.07993853e-01 2.04597935e-02
      4.10438716e-01 1.73658989e-02 4.11452413e-01 1.63268484e-02
      4.15069401e-01 1.32260006e-02 4.16581124e-01 1.21989548e-02
      4.20177400e-01 1.01224305e-02 4.22720492e-01 9.08774976e-03
      4.26517725e-01 8.05741735e-03 4.38705683e-01 8.15037265e-03
      4.42483991e-01 9.26353224e-03 4.45180297e-01 1.03770671e-02
      4.49043870e-01 1.25975860e-02 4.54295069e-01 1.70487352e-02
      4.56847012e-01 2.03855876e-02 4.59861487e-01 2.48710811e-02
      4.61070210e-01 2.82067899e-02</contour2d>
    <histogram type_id="opencv-matrix">
      <rows>20</rows>
      <cols>1</cols>
      <dt>f</dt>
      <data>
        0. 0. 0. 0. 0. 0. 0. 0. 0. 2.27376074e-03 9.97726202e-01 0. 0.
        0. 0. 0. 0. 0. 0. 0.</data></histogram></_>
  <_><id>6</id>
    <height>4.2614519596099854e-02</height>
    <contour2d>
      4.49029565e-01 -3.32035162e-02 4.47664738e-01 -2.77100839e-02
      4.46300030e-01 -2.44071055e-02 4.43679899e-01 -2.00043004e-02
      4.41126287e-01 -1.67090707e-02 4.36016351e-01 -1.23190284e-02
      4.32207406e-01 -1.01275733e-02 4.29684818e-01 -9.03239008e-03
      4.21541750e-01 -6.84517017e-03 4.18065101e-01 -6.82392158e-03
      4.12073016e-01 -7.83536956e-03 4.09081370e-01 -8.84851255e-03
      4.04607832e-01 -1.09001957e-02 4.03048635e-01 -1.19139934e-02
      4.00432855e-01 -1.39491465e-02 3.98051828e-01 -1.59826893e-02
      3.96173060e-01 -1.80359986e-02 3.93499494e-01 -2.20905822e-02
      3.92416418e-01 -2.41274387e-02 3.91539514e-01 -2.61789132e-02
      3.90293777e-01 -3.02474257e-02 3.89725506e-01 -3.42880152e-02
      3.89575869e-01 -3.84760424e-02 3.89931828e-01 -4.25193012e-02
      3.91385019e-01 -4.77559306e-02 3.93420637e-01 -5.19444160e-02
      3.94711763e-01 -5.40934950e-02 3.96375984e-01 -5.63204736e-02
      3.98278117e-01 -5.84449135e-02 4.00586754e-01 -6.06554635e-02
      4.04191226e-01 -6.29745200e-02 4.09080207e-01 -6.54050261e-02
      4.13935751e-01 -6.67901933e-02 4.21045929e-01 -6.72471523e-02
      4.26444918e-01 -6.66149929e-02 4.30917740e-01 -6.47044852e-02
      4.34714496e-01 -6.28061444e-02 4.41236466e-01 -5.78286499e-02
      4.45374846e-01 -5.26642390e-02 4.48991209e-01 -4.19227108e-02</contour2d>
    <histogram type_id="opencv-matrix">
      <rows>20</rows>
      <cols>1</cols>
      <dt>f</dt>
      <data>
        0. 0. 0. 0. 0. 0. 0. 0. 0. 3.03424359e-03 9.96965766e-01 0. 0.
        0. 0. 0. 0. 0. 0. 0.</data></histogram></_>
  <_><id>7</id>
    <height>4.2657434940338135e-02</height>
    <contour2d>
      4.15861934e-01 -4.57774773e-02 4.15711135e-01 -3.31183225e-02
      4.13134396e-01 -2.67199520e-02 4.10737664e-01 -2.24652626e-02
      4.08346891e-01 -1.92757472e-02 4.02670950e-01 -1.39777185e-02
      3.95534366e-01 -1.07767731e-02 3.90753448e-01 -9.69321281e-03
      3.81721765e-01 -9.60361771e-03 3.77330750e-01 -1.05735911e-02
      3.72860461e-01 -1.25372251e-02 3.69519979e-01 -1.44985551e-02
      3.65933806e-01 -1.74276177e-02 3.62994075e-01 -2.03776211e-02
      3.59762579e-01 -2.52727754e-02 3.58428091e-01 -2.81906687e-02
      3.57406974e-01 -3.11335139e-02 3.56472075e-01 -3.70500796e-02
      3.56409132e-01 -4.09973189e-02 3.57276142e-01 -4.69489507e-02
      3.58349085e-01 -5.09661883e-02 3.60699952e-01 -5.50993122e-02
      3.62779856e-01 -5.81974722e-02 3.64685237e-01 -6.02683499e-02
      3.68284464e-01 -6.35601208e-02 3.71672511e-01 -6.58166930e-02
      3.73722374e-01 -6.69394955e-02 3.77033591e-01 -6.81815296e-02
      3.90619099e-01 -6.91627190e-02 3.93967032e-01 -6.83575794e-02
      3.98646206e-01 -6.66279942e-02 4.02462035e-01 -6.48604408e-02
      4.07147884e-01 -6.09928556e-02 4.11999881e-01 -5.50132319e-02
      4.13369000e-01 -5.30088879e-02</contour2d>
    <histogram type_id="opencv-matrix">
      <rows>20</rows>
      <cols>1</cols>
      <dt>f</dt>
      <data>
        0. 0. 0. 0. 0. 0. 0. 0. 0. 1.23864575e-03 9.98761356e-01 0. 0.
        0. 0. 0. 0. 0. 0. 0.</data></histogram></_>
  <_><id>8</id>
    <height>4.2541921138763428e-02</height>
    <contour2d>
      3.65365148e-01 -4.72890250e-02 3.65354508e-01 -3.63246128e-02
      3.63010526e-01 -2.92604472e-02 3.60827357e-01 -2.52247658e-02
      3.58741283e-01 -2.22049002e-02 3.52430165e-01 -1.61624290e-02
      3.44255924e-01 -1.21307168e-02 3.29595923e-01 -1.19218864e-02
      3.23799878e-01 -1.37566729e-02 3.19838554e-01 -1.55906463e-02
      3.18593025e-01 -1.65000223e-02 3.13649118e-01 -2.11040657e-02
      3.12003464e-01 -2.29652952e-02 3.10103208e-01 -2.57300660e-02
      3.09088022e-01 -2.75673009e-02 3.07137579e-01 -3.21716592e-02
      3.05917412e-01 -3.67527194e-02 3.05791080e-01 -4.04541492e-02
      3.05905998e-01 -4.42034230e-02 3.06126118e-01 -4.61165383e-02
      3.07011276e-01 -4.98847067e-02 3.07990134e-01 -5.27483262e-02
      3.09855044e-01 -5.65956384e-02 3.11744541e-01 -5.95247857e-02
      3.15492213e-01 -6.35186806e-02 3.16662282e-01 -6.45909756e-02
      3.19536597e-01 -6.66802749e-02 3.23597163e-01 -6.89149648e-02
      3.26659918e-01 -7.01253489e-02 3.32819521e-01 -7.16006011e-02
      3.33830863e-01 -7.16806352e-02 3.39579672e-01 -7.10851401e-02
      3.45966280e-01 -6.96761310e-02 3.51298690e-01 -6.71594590e-02
      3.57539028e-01 -6.16668276e-02 3.62143278e-01 -5.60684688e-02</contour2d>
    <histogram type_id="opencv-matrix">
      <rows>20</rows>
      <cols>1</cols>
      <dt>f</dt>
      <data>
        0. 0. 0. 0. 0. 0. 0. 0. 0. 2.79999990e-03 9.97199953e-01 0. 0.
        0. 0. 0. 0. 0. 0. 0.</data></histogram></_>
  <_><id>9</id>
    <height>4.2775690555572510e-02</height>
    <contour2d>
      3.43706995e-01 -6.26596287e-02 3.41955006e-01 -5.67719303e-02
      3.40836704e-01 -5.47471270e-02 3.38683397e-01 -5.16986698e-02
      3.33398908e-01 -4.65603732e-02 3.30173671e-01 -4.44493480e-02
      3.26269150e-01 -4.23636958e-02 3.23253900e-01 -4.12654616e-02
      3.18636149e-01 -4.01487127e-02 3.12864274e-01 -3.98967825e-02
      3.08546871e-01 -4.05660830e-02 3.04902047e-01 -4.13525477e-02
      2.98445880e-01 -4.47639152e-02 2.95161933e-01 -4.72623445e-02
      2.92479396e-01 -4.98804785e-02 2.90883750e-01 -5.16685732e-02
      2.87974596e-01 -5.60157634e-02 2.87000120e-01 -5.77572659e-02
      2.85422504e-01 -6.31665587e-02 2.84992516e-01 -6.57399818e-02
      2.84818381e-01 -7.02097192e-02 2.84969121e-01 -7.38969147e-02
      2.85269111e-01 -7.67448619e-02 2.86993146e-01 -8.23315606e-02
      2.88001359e-01 -8.42863619e-02 2.89813161e-01 -8.72002169e-02
      2.93295711e-01 -9.11511034e-02 2.95492560e-01 -9.33527797e-02
      2.98417479e-01 -9.55655947e-02 3.00297886e-01 -9.67014283e-02
      3.05813849e-01 -9.91216153e-02 3.15285593e-01 -1.00147925e-01
      3.19167107e-01 -9.96370688e-02 3.22173208e-01 -9.90469009e-02
      3.28170478e-01 -9.68641266e-02 3.34511966e-01 -9.28329006e-02
      3.38683963e-01 -8.84539708e-02 3.42667729e-01 -8.10380578e-02
      3.43641967e-01 -7.72221461e-02</contour2d>
    <histogram type_id="opencv-matrix">
      <rows>20</rows>
      <cols>1</cols>
      <dt>f</dt>
      <data>
        0. 0. 0. 0. 0. 0. 0. 0. 0. 2.32738559e-03 9.96508956e-01 0. 0.
        0. 0. 0. 0. 0. 0. 1.16369280e-03</data></histogram></_>
  <_><id>10</id>
    <height>4.2369484901428223e-02</height>
    <contour2d>
      2.81910360e-01 -1.52942404e-01 2.83784091e-01 -1.51522174e-01
      2.86638767e-01 -1.48490950e-01 2.90216058e-01 -1.41776130e-01
      2.92212814e-01 -1.36713967e-01 2.92202532e-01 -1.23900704e-01
      2.91367829e-01 -1.20166585e-01 2.88555324e-01 -1.14273161e-01
      2.82124609e-01 -1.07039921e-01 2.64701217e-01 -1.04526363e-01
      2.64383942e-01 -1.54206336e-01 2.65365303e-01 -1.54246762e-01</contour2d>
    <histogram type_id="opencv-matrix">
      <rows>20</rows>
      <cols>1</cols>
      <dt>f</dt>
      <data>
        0. 0. 0. 0. 0. 0. 0. 0. 0. 0. 1. 0. 0. 0. 0. 0. 0. 0. 0. 0.</data></histogram></_>
  <_><id>11</id>
    <height>4.2025446891784668e-02</height>
    <contour2d>
      4.42935407e-01 -8.07906222e-03 4.42924261e-01 2.76764156e-03
      4.40263897e-01 1.03307460e-02 4.37568426e-01 1.46133229e-02
      4.35020447e-01 1.78023521e-02 4.29935515e-01 2.19893511e-02
      4.26085532e-01 2.40299888e-02 4.21159893e-01 2.60313451e-02
      4.17601228e-01 2.70000957e-02 4.06990945e-01 2.67224275e-02
      4.03241694e-01 2.55666841e-02 3.98466885e-01 2.33644973e-02
      3.96628857e-01 2.23121215e-02 3.92671049e-01 1.91057306e-02
      3.89508218e-01 1.59747209e-02 3.86049747e-01 9.77538992e-03
      3.84839058e-01 6.69536926e-03 3.83768886e-01 2.60505662e-03
      3.83378148e-01 -1.47677131e-03 3.83355588e-01 -4.53505618e-03
      3.83551955e-01 -7.59876985e-03 3.84641290e-01 -1.16915219e-02
      3.85804862e-01 -1.47741865e-02 3.88043553e-01 -1.89065430e-02
      3.89552712e-01 -2.10079458e-02 3.91320199e-01 -2.30752863e-02
      3.93509865e-01 -2.51812954e-02 3.97369832e-01 -2.84100305e-02
      4.02000427e-01 -3.06220800e-02 4.05429423e-01 -3.17653492e-02
      4.20504004e-01 -3.23009081e-02 4.27564353e-01 -2.93055717e-02
      4.36506778e-01 -2.20358707e-02 4.39995766e-01 -1.56143634e-02</contour2d>
    <histogram type_id="opencv-matrix">
      <rows>20</rows>
      <cols>1</cols>
      <dt>f</dt>
      <data>
        0. 0. 0. 0. 0. 0. 0. 0. 0. 1.29701686e-03 9.98702943e-01 0. 0.
        0. 0. 0. 0. 0. 0. 0.</data></histogram></_>
  <_><id>12</id>
    <height>4.1857600212097168e-02</height>
    <contour2d>
      4.74024147e-01 3.08443028e-02 4.71607983e-01 3.86115611e-02
      4.67281342e-01 4.39938456e-02 4.59179014e-01 5.02623580e-02
      4.51184094e-01 5.31441420e-02 4.46145147e-01 5.39857075e-02
      4.41144526e-01 5.37336729e-02 4.35719401e-01 5.23305908e-02
      4.32387024e-01 5.11287153e-02 4.30216670e-01 4.99793105e-02
      4.28377807e-01 4.87562418e-02 4.25578922e-01 4.64540385e-02
      4.22084779e-01 4.31207158e-02 4.19793218e-01 3.98519598e-02
      4.18611169e-01 3.76875773e-02 4.17210937e-01 3.44448835e-02
      4.16268587e-01 3.12590636e-02 4.15811300e-01 2.91009787e-02
      4.15480345e-01 2.59048399e-02 4.15477961e-01 2.16841847e-02
      4.15707797e-01 1.85324606e-02 4.17192340e-01 1.32807996e-02
      4.18642074e-01 1.01264166e-02 4.19847518e-01 8.01553857e-03
      4.22075093e-01 4.83979844e-03 4.26012486e-01 5.89172007e-04
      4.27284867e-01 -4.79536102e-04 4.31028455e-01 -2.62838509e-03
      4.35989529e-01 -4.79842955e-03 4.40884739e-01 -5.90357557e-03
      4.49900925e-01 -5.95632102e-03 4.53729808e-01 -4.88059735e-03
      4.59038585e-01 -2.70041917e-03 4.68707979e-01 5.07057272e-03
      4.72967476e-01 1.18069295e-02 4.73927647e-01 1.62864514e-02</contour2d>
    <histogram type_id="opencv-matrix">
      <rows>20</rows>
      <cols>1</cols>
      <dt>f</dt>
      <data>
        0. 0. 0. 0. 0. 0. 0. 0. 0. 1.35992747e-03 9.98640060e-01 0. 0.
        0. 0. 0. 0. 0. 0. 0.</data></histogram></_>
  <_><id>13</id>
    <height>4.1995465755462646e-02</height>
    <contour2d>
      4.70112652e-01 -4.84710187e-02 4.67604637e-01 -4.16905694e-02
      4.63632762e-01 -3.59889865e-02 4.59286481e-01 -3.25030275e-02
      4.52032506e-01 -2.79229172e-02 4.46816593e-01 -2.66877692e-02
      4.37931001e-01 -2.64588315e-02 4.33550060e-01 -2.73888912e-02
      4.28176165e-01 -2.93607786e-02 4.24721092e-01 -3.14082801e-02
      4.23319966e-01 -3.24176177e-02 4.20946270e-01 -3.44704986e-02
      4.18206394e-01 -3.75294536e-02 4.15968955e-01 -4.06304598e-02
      4.14759874e-01 -4.26917747e-02 4.12180871e-01 -4.88782860e-02
      4.11549509e-01 -5.61296307e-02 4.11754668e-01 -6.03703298e-02
      4.12350386e-01 -6.36453554e-02 4.13290441e-01 -6.68287873e-02
      4.14570212e-01 -7.00908005e-02 4.15705949e-01 -7.22718686e-02
      4.19275761e-01 -7.67592639e-02 4.22981888e-01 -8.02425295e-02
      4.24787194e-01 -8.15522969e-02 4.29272234e-01 -8.39796737e-02
      4.32823062e-01 -8.53177607e-02 4.44466591e-01 -8.63469839e-02
      4.48372215e-01 -8.55949298e-02 4.53687042e-01 -8.38659182e-02
      4.63186473e-01 -7.69305453e-02 4.68541384e-01 -6.84211776e-02
      4.69936967e-01 -6.40586317e-02</contour2d>
    <histogram type_id="opencv-matrix">
      <rows>20</rows>
      <cols>1</cols>
      <dt>f</dt>
      <data>
        0. 0. 0. 0. 0. 0. 0. 0. 0. 8.97666090e-04 9.99102354e-01 0. 0.
        0. 0. 0. 0. 0. 0. 0.</data></histogram></_>
  <_><id>14</id>
    <height>4.1623234748840332e-02</height>
    <contour2d>
      5.15594363e-01 -7.52509385e-02 5.13922274e-01 -7.16161802e-02
      5.09559393e-01 -6.43664375e-02 5.02086699e-01 -5.81362695e-02
      4.97944355e-01 -5.56296036e-02 4.94171500e-01 -5.43322265e-02
      4.83697891e-01 -5.37404194e-02 4.78602290e-01 -5.46481088e-02
      4.75629359e-01 -5.55962622e-02 4.71806616e-01 -5.76604456e-02
      4.68639553e-01 -5.96717335e-02 4.64276195e-01 -6.38302416e-02
      4.61847395e-01 -6.70350119e-02 4.58881289e-01 -7.23301843e-02
      4.57649618e-01 -7.66716599e-02 4.57239270e-01 -7.87884295e-02
      4.56900507e-01 -8.42214525e-02 4.57216084e-01 -8.87070820e-02
      4.58689690e-01 -9.43820179e-02 4.60229635e-01 -9.78803709e-02
      4.62563872e-01 -1.01369441e-01 4.65476453e-01 -1.05035402e-01
      4.68476832e-01 -1.07629843e-01 4.72458720e-01 -1.10267177e-01
      4.75193113e-01 -1.11680992e-01 4.82073039e-01 -1.13546871e-01
      4.83430356e-01 -1.13687806e-01 4.89932746e-01 -1.13160916e-01
      4.94410723e-01 -1.12541460e-01 4.98744607e-01 -1.10715866e-01
      5.07776320e-01 -1.04769118e-01 5.13922453e-01 -9.60907936e-02
      5.15392661e-01 -9.15526375e-02</contour2d>
    <histogram type_id="opencv-matrix">
      <rows>20</rows>
      <cols>1</cols>
      <dt>f</dt>
      <data>
        0. 0. 0. 0. 0. 0. 0. 0. 0. 2.38777464e-03 9.97612238e-01 0. 0.
        0. 0. 0. 0. 0. 0. 0.</data></histogram></_>
  <_><id>15</id>
    <height>4.1501939296722412e-02</height>
    <contour2d>
      5.21835804e-01 -1.23886064e-01 5.15804291e-01 -1.16175957e-01
      5.09741604e-01 -1.12010196e-01 5.06866038e-01 -1.10559881e-01
      5.01178145e-01 -1.08839191e-01 4.95618492e-01 -1.08301908e-01
      4.90000933e-01 -1.08879261e-01 4.84161019e-01 -1.10504165e-01
      4.82345104e-01 -1.11365937e-01 4.77944732e-01 -1.14229105e-01
      4.74279046e-01 -1.17285065e-01 4.71002072e-01 -1.21276677e-01
      4.68524486e-01 -1.25500768e-01 4.67153490e-01 -1.28673494e-01
      4.65921760e-01 -1.34113684e-01 4.65521395e-01 -1.38414621e-01
      4.65919107e-01 -1.43020064e-01 4.67208892e-01 -1.48757622e-01
      4.68210220e-01 -1.51039973e-01 4.71097916e-01 -1.55983388e-01
      4.73304868e-01 -1.58414826e-01 4.76051450e-01 -1.61082759e-01
      4.79662299e-01 -1.64134964e-01 4.82289046e-01 -1.65638268e-01
      4.88179862e-01 -1.67791069e-01 4.93457466e-01 -1.68529615e-01
      4.99294132e-01 -1.68344215e-01 5.05220771e-01 -1.67010054e-01
      5.15302241e-01 -1.60371557e-01 5.18540621e-01 -1.57405302e-01
      5.21821141e-01 -1.53251365e-01 5.24676979e-01 -1.44200146e-01
      5.24801195e-01 -1.32462934e-01</contour2d>
    <histogram type_id="opencv-matrix">
      <rows>20</rows>
      <cols>1</cols>
      <dt>f</dt>
      <data>
        0. 0. 0. 0. 0. 0. 0. 0. 0. 4.64684010e-04 9.99535322e-01 0. 0.
        0. 0. 0. 0. 0. 0. 0.</data></histogram></_></obj>
</opencv_storage>
